AUTHORS.rst
CONTRIBUTING.rst
HISTORY.rst
LICENSE
MANIFEST.in
README.rst
setup.cfg
setup.py
django_tinyschedule.egg-info/PKG-INFO
django_tinyschedule.egg-info/SOURCES.txt
django_tinyschedule.egg-info/dependency_links.txt
django_tinyschedule.egg-info/not-zip-safe
django_tinyschedule.egg-info/top_level.txt
tinyschedule/__init__.py
tinyschedule/admin.py
tinyschedule/forms.py
tinyschedule/models.py
tinyschedule/views.py
tinyschedule/migrations/0001_initial.py
tinyschedule/migrations/__init__.py