Metadata-Version: 1.1
Name: django-tinyschedule
Version: 0.2
Summary: A small package for managing schedules in Django
Home-page: https://github.com/jgeskens/django-tinyschedule
Author: Jef Geskens
Author-email: jef.geskens@gmail.com
License: BSD
Keywords: django-tinyschedule
Platform: UNKNOWN
Classifier: Development Status :: 2 - Pre-Alpha
Classifier: Framework :: Django
Classifier: Intended Audience :: Developers
Classifier: License :: OSI Approved :: BSD License
Classifier: Natural Language :: English
Classifier: Programming Language :: Python :: 2
Classifier: Programming Language :: Python :: 2.6
Classifier: Programming Language :: Python :: 2.7
Classifier: Programming Language :: Python :: 3
Classifier: Programming Language :: Python :: 3.5
